Metadata-Version: 1.0
Name: change-bootstrap
Version: 0.0.2
Summary: change bootstrap
Home-page: http://changedeploy.cloud
Author: maoxuepeng
Author-email: maoxuepeng@gmail.com
License: MIT Licence
Keywords: pip,deployment,bootstrap,change
Platform: any
